{
  "id": "heritage-mclaren-f1-three-seater",
  "slug": "mclaren-f1-three-seater-heritage",
  "type": "HERITAGE",
  "status": "published",
  "kind": "CAR",
  "maker": "McLaren",
  "brandName": "McLaren",
  "title": "【完全保存版】運転席は真ん中にあった。マクラーレンF1が示した「速さの設計図」",
  "titleJa": "【完全保存版】運転席は真ん中にあった。マクラーレンF1が示した「速さの設計図」",
  "seoTitle": "マクラーレンF1の真実｜中央座席・V12・軽量化が作った“速さの設計図”",
  "seoDescription": "中央座席、BMW製6.1L V12、カーボンモノコック、金箔断熱——マクラーレンF1は“速い車の作り方”を構造で語った。90年代に完成した設計思想を、章立てで読み解く。",
  "createdAt": "2026-01-03",
  "publishedAt": "2026-01-03",
  "updatedAt": "2026-01-03",
  "heroTitle": "運転席は、真ん中に。",
  "heroCaption": "中央座席、自然吸気V12、徹底した軽量化。マクラーレンF1は“速さ”をスペックではなく設計で定義した。",
  "heroImage": "/images/heritage/hero_default.jpg",
  "heroImageCredit": "",
  "heroTone": "dark",
  "eraLabel": "1992–1998",
  "keyModels": [
    "McLaren F1 (Road)",
    "F1 LM",
    "F1 GTR"
  ],
  "highlights": [
    "運転席を車体中心に置くことで、視界と入力のズレを最小化した「人間中心設計」",
    "BMW製6.1L自然吸気V12と、金箔断熱に象徴される徹底した熱対策",
    "カーボンモノコックと軽量化により、反応の速さ＝体感速度を最大化",
    "最高速記録以上に重要な、“速さが成立するシステム”という思想"
  ],
  "summary": "中央座席、自然吸気V12、カーボンモノコック。マクラーレンF1は“速さの作り方”を、派手な演出ではなく構造で残した。90年代に完成した設計思想を、今の視点で読み解く。",
  "body": "【序章：スーパーカーの“答え合わせ”が90年代にあった】\nいまのハイパーカーは、電動化、ハイブリッド化、そして「制御」が主役になった。\n速さは、馬力や排気量よりも、タイヤと電子制御と空力の整合で決まる。これは正しい。\n\nけれど、速さの“設計図”を一枚の紙に描けと言われたら、答えは意外と古い。\nそれが、1992年に生まれたマクラーレンF1だ。\n\n中央座席、自然吸気V12、カーボンモノコック、徹底した軽量化。\nそして「3人乗り」という異物感。\nF1はスペックの奇抜さで語られがちだが、本質はもっと地味で、もっと怖い。\n“速い車を作るとき、人間と機械のどこに手を入れるべきか”が、設計の順番ごと残っているのだ。\n\n### いまの速さと、F1の速さは種類が違う\n現代のハイパーカーは、制御と空力と電動化で速さを作る。\nだから速い。\nしかし速さの“作り方”が高度になるほど、ドライバーが触れる部分は薄くなる。\nマクラーレンF1は、その逆だ。\n速さの要素が、物理として剥き出しになっている。\n視界、重心、熱、重量、そして入力の遅れ。\nそれらを一つずつ潰していくことで、結果として異常な速さに到達した。\n\n3人乗りという奇抜さも、実は合理から出ている。\n「運転の中心」を文字通り車体の中心へ置く。\nそのために座席配置を再構成する。\n奇抜に見えるのは、合理が徹底されているからだ。\n\n__SPEC_HEADING__マクラーレンF1を語るキーワード\n・3人乗りセンターシート / ドライバー中心のパッケージ\n・BMW製自然吸気V12 / 熱対策（遮熱）\n・カーボンモノコック / 軽量化（約1.1トン級）\n・最高速386.4km/h（量産車としての象徴）\n・GTRがル・マンを制した“答え合わせ”\n\n【第1章：運転席を真ん中に置く。視界と感覚の設計】\nマクラーレンF1の最大の異常点は、最高速でも馬力でもない。\n運転席が“真ん中”にあることだ。\n\nこれは単なる話題作りではない。\n中央座席は、左右の死角を均等にし、車幅感覚を「手の延長」に変える。\nステアリングのセンターと、車体のセンターと、視線のセンターが一致する。\n運転とは本来、左右差のない情報を受け取って、左右差のない入力を返す行為だ。\nF1はその当たり前を、パッケージングでやり切った。\n\n同乗者席が左右に1席ずつ置かれているのも象徴的だ。\nスーパーカーが「見せびらかすための二人乗り」を選ぶのに対し、F1は「走るための三人乗り」を選んだ。\n同乗者は“飾り”ではなく、重心バランスの一部であり、旅の一部であり、体験の一部だ。\nここにあるのは豪華さではなく、機能としての合理である。\n\nそして、中央座席は副作用も生む。\n乗り降りは簡単ではないし、街乗りで気楽に扱える車でもない。\nそれでもF1がこのレイアウトを選んだのは、「運転」という体験の品質を最上段に置いたからだ。\n最速を狙うのではなく、最も正しい運転姿勢を作る。\n速さは、その“姿勢”の上に乗る。\n\n### センターシートが生む「誤差の少なさ」\n運転席が中央にあると、左右の感覚の誤差が減る。\n車幅感覚が掴みやすく、コーナーのクリップに寄せる動作が素直になる。\nそしてステアリングの入力に対して、車体が“まっすぐ”返ってくる。\nこれは単なる気分の問題ではない。\n操作の誤差が減れば、タイヤの仕事が増える。\nタイヤの仕事が増えれば、速さが再現性を持つ。\nセンターシートは、速さを“特別な才能”から“設計の結果”へ寄せる。\n\nさらにF1は、センターシートを成立させるために室内の作り方も特別だ。\n同乗者席の配置、荷物の置き場、乗降性。\nスーパーカーの非日常を残しつつ、長距離を走れる実用性を捨てていない。\nこの矛盾の処理が、F1の設計の怖さでもある。\n\n【第2章：BMW製6.1L V12と“熱”の戦い】\nF1の心臓はBMWが供給した6.1L自然吸気V12（通称S70/2）だ。\n大排気量でありながらレスポンスを失わず、回して気持ちよく、そして壊れにくい。\n「速さ」と「耐久」を同居させるために、最初から量産品質を前提に設計された。\n\nここで重要なのは、F1が“ピーキーなレーシングエンジン”を選ばなかったことだ。\nF1は、極端に速いだけでは足りない。\n渋滞でも、雨でも、長距離でも、同じ調子で走る必要がある。\nその要求は、スーパーカーというより「信頼性の高い航空機」に近い。\n\nただし、巨大なV12をミッドに置くと、次の敵が現れる。\n熱である。\n\nエンジンはパワーを作るが、同時に熱を作る。\n熱は配線を傷め、樹脂を劣化させ、室内を不快にし、最悪の場合は走行を止める。\nF1がエンジンルームに金箔を貼った話は有名だが、あれは装飾ではない。\n熱を遮るために、最も確実な素材を“そのまま”使っただけだ。\n\n熱対策は、速さの裏方ではない。\n熱を制す者が、実用性と信頼性を手に入れる。\nF1はそこを、見た目の派手さではなく、物理で殴っている。\n\n### V12は「パワー」より「品格」を担う\nF1のV12が特別なのは、ただ大排気量だからではない。\n自然吸気で、レスポンスと伸びを両立し、長時間の高負荷でも調子を崩しにくい。\nスーパーカーでありながら、耐久の発想を持っている。\nここがF1の異常さだ。\n\n熱との戦いは、象徴的に“金色”で語られることがある。\nエンジンルームの遮熱は、それほど切実だった。\n熱は性能を奪うだけでなく、信頼を奪う。\n信頼が揺らぐと、ドライバーは踏めなくなる。\n踏めない車は、どれだけ速くても“速くない”。\nF1は、熱対策を速さの一部として扱った。\n\n【第3章：カーボンモノコックと1,138kg。軽さは性能の総量】\nF1の凄みは、数字を並べると一気に伝わる。\nカーボンモノコックで剛性を確保しながら、車重は約1.1トン級に収めた。\nこの「軽いのに強い」という矛盾の解決が、あらゆる性能を底上げする。\n\n同じ馬力でも、軽ければ加速が鋭くなる。\n同じタイヤでも、軽ければ曲がりが深くなる。\n同じブレーキでも、軽ければ止まりが短くなる。\nそして何より、軽い車は“反応が速い”。\n速さの体感は、0-100の数字より、入力に対する遅れの少なさで決まる。\n\nF1は、軽量化を「削る」ではなく「設計する」でやった。\n最小限の装備、最短の配線、無駄のない機構。\n当時としては思い切りすぎるほどの“足し算拒否”だ。\nその結果、ステアリングに力は要るが、情報が濃い。\nブレーキも、路面も、温度も、全部が手元に戻ってくる。\n\nフェラーリF40が荒々しい「軽さ」なら、F1は精密な「軽さ」だ。\n快適性を捨てずに軽い。重さをごまかさずに剛い。\nこれがハイパーカーの設計思想を一段引き上げた。\n\n### 軽さは、すべての性能に同時に効く\n軽い車は、加速だけでなく、制動と旋回も強くなる。\nさらにタイヤとブレーキの負担が減り、連続走行で性能が落ちにくい。\nつまり軽さは、速さの“総量”を増やす。\nF1が1.1トン級に収めた価値は、ここにある。\n\nそして軽さは、車の反応を「透明」にする。\n入力してから動くまでの遅れが減るほど、車はドライバーの手足になる。\n現代の車は制御で遅れを隠せる。\nF1は、遅れそのものを消す方向へ振った。\nだから乗り手は、機械の輪郭を濃く感じる。\n\n【第4章：386.4km/hより大切なもの。F1が残した思想】\n1990年代のスーパーカー戦争は、記録の奪い合いだった。\nF1は量産車の最高速記録を打ち立て、歴史に名を残した。\nだが、F1の本質は“記録”ではない。\n\n中央座席は、ドライバー中心の哲学だ。\n軽量化は、車の反応を磨くための哲学だ。\n熱対策は、長く走らせるための哲学だ。\nつまりF1は、スペック競争の外側に「作り方の基準」を置いた。\n\nその基準は、いまも効く。\n新しい時代の車がどれだけ速くても、重くて、鈍くて、熱に負けるなら、結局は“続かない”。\nF1は、速さを「一発の数字」ではなく、「成立するシステム」として完成させた。\n\nそして、F1の思想は後継に繰り返し現れる。\nカーボンモノコックは当たり前になり、空力は高度化し、制御は賢くなった。\nそれでも「軽さ」「熱」「視界」という根は変わらない。\nF1はそれを、派手な演出ではなく、構造で刻んだ。\n\n### 記録は結果であって、目的ではない\n最高速386.4km/hは、歴史の見出しとして強い。\nだがF1の本質は、そこへ到達する“過程の設計”にある。\n視界を確保し、重心を整え、熱を制し、軽さで全てを底上げする。\n派手な魔法ではなく、地味な前提条件の積み上げ。\nこれがF1の思想だ。\n\nさらにF1は、レースでも答え合わせをした。\nGTRがル・マンを制した事実は象徴的だ。\nロードカー的な思想が、耐久の舞台で通用した。\n速さを「一発」ではなく「続く速さ」として定義していたからこそ、物語がつながる。\n\n【終章：電動化の時代に、F1を読む理由】\n電動化は正しい。制御も正しい。これからの速さは、さらに賢くなる。\nけれど、速さの根っこは変わらない。\n視界、重心、熱、重量、入力遅れ。最後は物理だ。\n\nマクラーレンF1は、物理の教科書のように、速さの要素を一枚ずつ剥がして見せてくれる。\nそして不思議なことに、その“古い答え”が、いま一番新しく見える。\n\nF1を読む理由は、懐古ではない。\n設計の基礎が、いまも変わらないからだ。\n視界は、怖さを減らす。\n重量は、全性能へ同時に効く。\n熱は、信頼を奪う。\n信頼が揃うほど、ドライバーは踏める。\nこの当たり前は、どれだけ時代が変わっても残る。\n\nだからF1は、未来の車を読むための辞書にもなる。\n電動化で速さの作り方が変わっても、「速さの条件」は変わらない。\nF1はその条件を、これ以上ない純度で見せた。\n古い答えが新しく見えるのは、設計の筋が正しいからだ。\n\nもう一つ、F1が今も特別に見える理由がある。\nそれは“矛盾の解き方”が美しいことだ。\nスーパーカーの非日常性を残しながら、長距離を走れる現実も捨てない。\n尖りを見せながら、信頼を確保する。\nこの矛盾を解くには、派手な装備より設計の順番が要る。\n\nだからマクラーレンF1は、博物館に置くための存在ではない。\n工学として読み返すための存在だ。\n速さがどれだけ変化しても、設計の順番が正しいものは古びない。\nF1は、そのことを静かに証明し続けている。",
  "tags": [
    "mclaren",
    "mclaren-f1",
    "hypercar",
    "na-v12",
    "three-seater",
    "carbon",
    "1990s",
    "gordon-murray",
    "engineering",
    "lightweight"
  ],
  "intentTags": [
    "supercar",
    "hypercar",
    "engineering"
  ],
  "relatedCarSlugs": [
    "mclaren-f1",
    "ferrari-f40",
    "ferrari-f50",
    "lamborghini-diablo-vt-60"
  ],
  "relatedGuideSlugs": [
    "car-budget-simulation",
    "import-maintenance-cost",
    "oldtimer-maintenance-budget"
  ],
  "relatedColumnSlugs": [
    "technical-supercar-vs-hypercar",
    "technical-na-vs-turbo",
    "technical-why-sound-is-special"
  ],
  "relatedHeritageSlugs": [
    "supercar-parts-bin-engineering-heritage"
  ],
  "sections": [
    {
      "title": "序章：スーパーカーの“答え合わせ”が90年代にあった",
      "summary": "電動化と制御が主役になった今だからこそ、マクラーレンF1の設計思想は“速さの教科書”として読み直せる。奇抜さではなく、順番と理由のある速さを掘り下げる。",
      "carSlugs": [
        "mclaren-f1",
        "ferrari-f40",
        "lamborghini-diablo-vt-60"
      ],
      "guideSlugs": [],
      "columnSlugs": [
        "technical-supercar-vs-hypercar"
      ]
    },
    {
      "title": "第1章：運転席を真ん中に置く。視界と感覚の設計",
      "summary": "中央座席はネタではない。左右差のない視界と車幅感覚、入力の素直さを作るための人間中心設計だった。F1が“運転体験”を最優先した理由を整理する。",
      "carSlugs": [
        "mclaren-f1"
      ],
      "guideSlugs": [],
      "columnSlugs": []
    },
    {
      "title": "第2章：BMW製6.1L V12と“熱”の戦い",
      "summary": "速さと耐久を両立させるために選ばれたBMW製V12。そしてミッド配置が呼び込む最大の敵＝熱。金箔断熱に象徴される熱対策は、実用性と信頼性の核心だった。",
      "carSlugs": [
        "mclaren-f1",
        "ferrari-f50"
      ],
      "guideSlugs": [
        "import-maintenance-cost"
      ],
      "columnSlugs": [
        "technical-why-sound-is-special"
      ]
    },
    {
      "title": "第3章：カーボンモノコックと1,138kg。軽さは性能の総量",
      "summary": "軽い車はあらゆる性能を底上げする。F1は軽量化を“削る”のではなく“設計する”で実現し、反応の速さ＝体感速度を最大化した。F40との質感の違いも含めて見る。",
      "carSlugs": [
        "mclaren-f1",
        "ferrari-f40"
      ],
      "guideSlugs": [
        "car-budget-simulation"
      ],
      "columnSlugs": [
        "technical-na-vs-turbo"
      ]
    },
    {
      "title": "第4章：386.4km/hより大切なもの。F1が残した思想",
      "summary": "記録よりも重要なのは、速さを“成立するシステム”として完成させたこと。視界・重量・熱という根を押さえたF1の基準は、いまもハイパーカーの設計に効いている。",
      "carSlugs": [
        "mclaren-f1"
      ],
      "guideSlugs": [
        "oldtimer-maintenance-budget"
      ],
      "columnSlugs": [
        "technical-supercar-vs-hypercar"
      ]
    },
    {
      "title": "終章：電動化の時代に、F1を読む理由",
      "summary": "制御が賢くなっても、最後は物理が残る。F1は速さの要素を一枚ずつ剥がして見せる“構造の文章”だ。古い答えが、いま一番新しく見える理由をまとめる。",
      "carSlugs": [
        "mclaren-f1"
      ],
      "guideSlugs": [],
      "columnSlugs": []
    }
  ],
  "canonicalUrl": null,
  "ogImageUrl": null,
  "publicState": "noindex",
  "parentPillarId": "/heritage",
  "relatedClusterIds": [],
  "primaryQuery": "【完全保存版】運転席は真ん中にあった。マクラーレンF1が示した「速さの設計図」",
  "updateReason": "initial-import",
  "sources": []
}