{
  "id": "nissan-gt-r-r35-early",
  "slug": "nissan-gt-r-r35-early",
  "name": "Nissan GT-R (R35) early",
  "maker": "Nissan",
  "releaseYear": 2007,
  "difficulty": "advanced",
  "bodyType": "coupe",
  "segment": "スーパースポーツ",
  "heritageRefs": [],
  "category": "",
  "grade": "GT-R R35 (early)",
  "summary": "速さを“再現可能”にした日本車。才能ではなく、統合制御で速いという価値観を量産に落とした。",
  "summaryLong": "初期R35 GT-Rは、国産ハイパフォーマンスの作り方を切り替えた象徴です。速さの理由が、エンジンだけではなく、発進・変速・駆動配分・姿勢制御の“セット”にある。\n\n乗ると、速さが均一で、怖さが丸い。これが好きかどうかで評価が割れた。けれど今となっては、世界の速さがこの方向へ進んだことが分かる。\n\nいま買う目線では、性能より履歴。DCTやデフ、冷却、電装の整合が取れていない個体は、速さが出ないだけでなく、違和感が積み重なる。逆に整った個体は、今でも“速さの基準”として成立します。",
  "heroImage": "/images/cars/nissan-gt-r-r35-early-hero.jpg",
  "mainImage": "/images/cars/nissan-gt-r-r35-early-main.jpg",
  "imageUrl": "/images/cars/nissan-gt-r-r35-early-hero.jpg",
  "gallery": [
    "/images/cars/nissan-gt-r-r35-early-front.jpg",
    "/images/cars/nissan-gt-r-r35-early-side.jpg",
    "/images/cars/nissan-gt-r-r35-early-interior.jpg"
  ],
  "engine": "Front V6 3.8 Twin Turbo (VR38DETT)",
  "powerPs": 480,
  "torqueNm": 588,
  "transmission": "6DCT",
  "drive": "AWD",
  "fuel": "ハイオク",
  "fuelEconomy": "目安: 5〜9 km/L",
  "priceNew": "当時: 700万〜1000万円台（仕様差）",
  "priceUsed": "450万〜1200万円（相場変動）",
  "strengths": [
    "統合制御で、誰でも速さを再現しやすい（路面と天候に強い）。",
    "高速域の安定と巡航余裕が大きく、ツーリング適性が高い。",
    "ソフトで性格が変わるため、整備とセットアップで伸びしろがある。",
    "世界基準の性能を国産で体験できる。"
  ],
  "weaknesses": [
    "駆動・変速・電装のどれかが崩れると、違和感が大きい。",
    "整備は専門性が高く、店と主治医選びが重要。",
    "熱管理の履歴が性能と寿命を左右しやすい。",
    "タイヤ・ブレーキなど消耗品コストが高い。"
  ],
  "troubleTrends": [
    "DCTの挙動（温間時のショック、異音、学習状態）は試乗で確認したいです。",
    "デフ周りの滲み、異音、作動の違和感は要チェックです。",
    "冷却系（ラジエーター、配管、オイルクーラー）の手当て履歴で差が出ます。",
    "バッテリー電圧や配線の乱れが電子制御に影響することがあります。"
  ],
  "costImpression": "“安く買う”と“安く乗る”が噛み合いにくい車。履歴の良い個体を選ぶほど、結果的に安い。",
  "relatedNewsIds": [],
  "relatedColumnSlugs": [
    "column-software-defined-performance-r35"
  ],
  "relatedGuideSlugs": [
    "guide-buy-early-r35-gtr-checklist"
  ],
  "relatedCarSlugs": [
    "lexus-lfa-2010",
    "mitsubishi-lancer-evolution-x-final"
  ],
  "tags": [
    "Nissan",
    "GT-R",
    "R35",
    "VR38DETT",
    "AWD",
    "DCT",
    "2000s"
  ],
  "relatedHeritageSlugs": [
    "japan-software-performance-era-heritage"
  ],
  "intentTags": [
    "performance",
    "AWD",
    "electronics",
    "2000s",
    "heritage",
    "touring"
  ],
  "purchasePriceSafe": "安全ライン：650〜950万円前後（整備履歴と主治医重視）",
  "maintenanceSimulation": {
    "yearlyRoughTotal": "年間70〜140万円"
  },
  "maintenanceCostYenPerYear": 950000,
  "type": "CAR",
  "status": "published",
  "title": "Nissan Nissan GT-R (R35) early",
  "makerKey": "nissan",
  "createdAt": null,
  "publishedAt": null,
  "updatedAt": "2026-01-30",
  "seoTitle": null,
  "seoDescription": null,
  "titleJa": null,
  "canonicalUrl": null,
  "ogImageUrl": null,
  "publicState": "noindex",
  "parentPillarId": "/cars/makers/nissan",
  "relatedClusterIds": [],
  "primaryQuery": "Nissan GT-R (R35) early",
  "updateReason": "initial-import",
  "sources": []
}
